matengine/__init__.py
matengine/characterization/__init__.py
matengine/discovery/__init__.py
matengine/generation/__init__.py
matengine/generation/decisiontree.py
matengine/generation/filters.py
matengine/generation/generators.py
matengine/generation/plurigaussian.py
matengine/simulation/__init__.py
matengine/utils/__init__.py
matengine/utils/plotting.py
matengine-0.0.8.dist-info/LICENSE
matengine-0.0.8.dist-info/METADATA
matengine-0.0.8.dist-info/WHEEL
matengine-0.0.8.dist-info/RECORD
