Metadata-Version: 2.1
Name: matengine
Version: 0.0.8
Summary: A library for material discovery
License: MIT
Author: Evan John Ricketts
Author-email: rickettse1@cardiff.ac.uk
Requires-Python: >=3.10,<3.13
Classifier: Development Status :: 2 - Pre-Alpha
Classifier: Intended Audience :: Science/Research
Classifier: License :: OSI Approved :: MIT License
Classifier: Operating System :: OS Independent
Classifier: Programming Language :: Python :: 3
Classifier: Programming Language :: Python :: 3.10
Classifier: Programming Language :: Python :: 3.11
Classifier: Programming Language :: Python :: 3.12
Classifier: Topic :: Scientific/Engineering
Requires-Dist: gstools (>=1.5.3,<2.0.0)
Requires-Dist: matplotlib (>=3.9.2,<4.0.0)
Requires-Dist: numpy (==2.0.0)
Requires-Dist: pyvista (>=0.44.1,<0.45.0)
Requires-Dist: scikit-image (>=0.24.0,<0.25.0)
Requires-Dist: scipy (>=1.14.1,<2.0.0)
Requires-Dist: torch (>=2.5.0,<3.0.0)
